selenium_behave/__init__.py
selenium_behave/cli.py
selenium_behave/steps/Web_And_App_Error.py
selenium_behave/steps/__init__.py
selenium_behave/steps/agentic_steps.py
selenium_behave/steps/chatbot_steps.py
selenium_behave/steps/common_steps.py
selenium_behave/steps/faq_eval_steps.py
selenium_behave/steps/voicebot_steps.py
selenium_behave/utils/__init__.py
selenium_behave/utils/agentic_helper.py
selenium_behave/utils/bedrock_client.py
selenium_behave/utils/bot_client.py
selenium_behave/utils/chatbot_client.py
selenium_behave/utils/config_loader.py
selenium_behave/utils/evaluation_utils.py
selenium_behave/utils/excel_utils.py
selenium_behave/utils/report_generator.py
selenium_behave/utils/ui_utils.py
selenium_behave/utils/voice_handler.py
selenium_behave-2.0.3.dist-info/licenses/LICENSE
selenium_behave-2.0.3.dist-info/METADATA
selenium_behave-2.0.3.dist-info/WHEEL
selenium_behave-2.0.3.dist-info/entry_points.txt
selenium_behave-2.0.3.dist-info/top_level.txt
selenium_behave-2.0.3.dist-info/RECORD
